poetry_plugin_updater/__init__.py
poetry_plugin_updater/command.py
poetry_plugin_updater/plugins.py
poetry_plugin_updater/updater.py
poetry_plugin_updater-0.0.3.dist-info/METADATA
poetry_plugin_updater-0.0.3.dist-info/WHEEL
poetry_plugin_updater-0.0.3.dist-info/entry_points.txt
poetry_plugin_updater-0.0.3.dist-info/RECORD
